CHANGELOG.rst
LICENSE
README.rst
dev-only.txt
dev-req.txt
requirements.txt
setup.py
hyde/__init__.py
hyde/engine.py
hyde/exceptions.py
hyde/generator.py
hyde/layout.py
hyde/main.py
hyde/model.py
hyde/plugin.py
hyde/publisher.py
hyde/server.py
hyde/site.py
hyde/template.py
hyde/util.py
hyde/version.py
hyde.egg-info/PKG-INFO
hyde.egg-info/SOURCES.txt
hyde.egg-info/dependency_links.txt
hyde.egg-info/entry_points.txt
hyde.egg-info/not-zip-safe
hyde.egg-info/requires.txt
hyde.egg-info/top_level.txt
hyde/ext/__init__.py
hyde/ext/plugins/__init__.py
hyde/ext/plugins/blog.py
hyde/ext/plugins/css.py
hyde/ext/plugins/depends.py
hyde/ext/plugins/images.py
hyde/ext/plugins/js.py
hyde/ext/plugins/languages.py
hyde/ext/plugins/meta.py
hyde/ext/plugins/sphinx.py
hyde/ext/plugins/structure.py
hyde/ext/plugins/text.py
hyde/ext/plugins/urls.py
hyde/ext/plugins/vcs.py
hyde/ext/publishers/__init__.py
hyde/ext/publishers/dvcs.py
hyde/ext/publishers/pyfs.py
hyde/ext/publishers/pypi.py
hyde/ext/publishers/ssh.py
hyde/ext/templates/__init__.py
hyde/ext/templates/jinja.py
hyde/layouts/basic/README.markdown
hyde/layouts/basic/info.yaml
hyde/layouts/basic/site.yaml
hyde/layouts/basic/content/about.html
hyde/layouts/basic/content/index.html
hyde/layouts/basic/content/blog/angry-post.html
hyde/layouts/basic/content/blog/atom.xml
hyde/layouts/basic/content/blog/excerpts.xml
hyde/layouts/basic/content/blog/happy-post.html
hyde/layouts/basic/content/blog/index.html
hyde/layouts/basic/content/blog/meta.yaml
hyde/layouts/basic/content/blog/sad-post.html
hyde/layouts/basic/content/media/meta.yaml
hyde/layouts/basic/content/media/css/site.css
hyde/layouts/basic/content/media/css/syntax.css
hyde/layouts/basic/content/media/images/airport.png
hyde/layouts/basic/content/media/images/apple-touch-icon.png
hyde/layouts/basic/content/media/images/dark.png
hyde/layouts/basic/content/media/images/favicon.ico
hyde/layouts/basic/content/media/js/libs/dd_belatedpng.js
hyde/layouts/basic/content/media/js/libs/jquery-1.5.1.min.js
hyde/layouts/basic/content/media/js/libs/meta.yaml
hyde/layouts/basic/content/media/js/libs/modernizr-1.7.min.js
hyde/layouts/basic/content/portfolio/index.html
