Metadata-Version: 1.1
Name: hyde
Version: 0.8.9
Summary: hyde is a static website generator
Home-page: http://hyde.github.io
Author: hyde developers
Author-email: hyde-dev@googlegroups.com
License: MIT
Platform: UNKNOWN
Classifier: Development Status :: 4 - Beta
Classifier: Environment :: Console
Classifier: Intended Audience :: End Users/Desktop
Classifier: Intended Audience :: Developers
Classifier: Intended Audience :: System Administrators
Classifier: License :: OSI Approved :: MIT License
Classifier: Operating System :: MacOS :: MacOS X
Classifier: Operating System :: Unix
Classifier: Operating System :: POSIX
Classifier: Operating System :: Microsoft :: Windows
Classifier: Programming Language :: Python
Classifier: Topic :: Software Development
Classifier: Topic :: Software Development :: Build Tools
Classifier: Topic :: Software Development :: Code Generators
Classifier: Topic :: Internet
Classifier: Topic :: Internet :: WWW/HTTP :: Site Management
Requires: python (>= 2.7)
